lfsr.v
// N-bit Fibonacci LFSR
// Ashan Liyanage
module lfsr #(parameter MSB=16) ( 
	input 		clk,
	input 		rstn,
	output reg 	[MSB-1:0]out			
);

always @ (posedge clk) begin
	if(!rstn)
		out <= 1;
	else begin
		out[MSB-2:0] <= out[MSB-1:1];
		out[MSB-1]	<= (((out[0]^out[2]) ^ out[3]) ^  out[5]);  
	end
end
endmodule

tb_lfsr.v
// Test bench for N-bit Fibonacci LFSR
// Ashan Liyanage
`timescale 1ns/1ns
module tb_lfsr;
parameter MSB = 16;
reg clk;
reg rstn;
wire [MSB-1:0]out;

always #5 clk = ~clk; // 10ns clock time period. 100MHz

lfsr #(.MSB(MSB)) u0 (	.clk(clk),
						.rstn(rstn),
						.out(out));

initial begin
	$dumpfile("wave.vcd");
	$dumpvars(1);
	clk <= 0;
	rstn<=0;
	
	repeat (4) @ (negedge clk);

	rstn <= 1;
	
	repeat (100) @ (negedge clk);

	$finish;
end

initial
      $monitor ("clk=%0b rstn=%b, out=0x%4h", clk, rstn, out);

endmodule

wave.vcd
$date
	Sat Jul 18 20:50:15 2020
$end
$version
	Icarus Verilog
$end
$timescale
	1ns
$end
$scope module tb_lfsr $end
$var wire 16 ! out [15:0] $end
$var reg 1 " clk $end
$var reg 1 # rstn $end
$upscope $end
$enddefinitions $end
#0
$dumpvars
0#
0"
bx !
$end
#5
b1 !
1"
#10
0"
#15
1"
#20
0"
#25
1"
#30
1#
0"
#35
b1000000000000000 !
1"
#40
0"
#45
b100000000000000 !
1"
#50
0"
#55
b10000000000000 !
1"
#60
0"
#65
b1000000000000 !
1"
#70
0"
#75
b100000000000 !
1"
#80
0"
#85
b10000000000 !
1"
#90
0"
#95
b1000000000 !
1"
#100
0"
#105
b100000000 !
1"
#110
0"
#115
b10000000 !
1"
#120
0"
#125
b1000000 !
1"
#130
0"
#135
b100000 !
1"
#140
0"
#145
b1000000000010000 !
1"
#150
0"
#155
b100000000001000 !
1"
#160
0"
#165
b1010000000000100 !
1"
#170
0"
#175
b1101000000000010 !
1"
#180
0"
#185
b110100000000001 !
1"
#190
0"
#195
b1011010000000000 !
1"
#200
0"
#205
b101101000000000 !
1"
#210
0"
#215
b10110100000000 !
1"
#220
0"
#225
b1011010000000 !
1"
#230
0"
#235
b101101000000 !
1"
#240
0"
#245
b10110100000 !
1"
#250
0"
#255
b1000001011010000 !
1"
#260
0"
#265
b100000101101000 !
1"
#270
0"
#275
b10000010110100 !
1"
#280
0"
#285
b1000001011010 !
1"
#290
0"
#295
b1000100000101101 !
1"
#300
0"
#305
b100010000010110 !
1"
#310
0"
#315
b1010001000001011 !
1"
#320
0"
#325
b101000100000101 !
1"
#330
0"
#335
b10100010000010 !
1"
#340
0"
#345
b1010001000001 !
1"
#350
0"
#355
b1000101000100000 !
1"
#360
0"
#365
b1100010100010000 !
1"
#370
0"
#375
b110001010001000 !
1"
#380
0"
#385
b1011000101000100 !
1"
#390
0"
#395
b1101100010100010 !
1"
#400
0"
#405
b1110110001010001 !
1"
#410
0"
#415
b1111011000101000 !
1"
#420
0"
#425
b111101100010100 !
1"
#430
0"
#435
b1011110110001010 !
1"
#440
0"
#445
b1101111011000101 !
1"
#450
0"
#455
b110111101100010 !
1"
#460
0"
#465
b1011011110110001 !
1"
#470
0"
#475
b101101111011000 !
1"
#480
0"
#485
b1010110111101100 !
1"
#490
0"
#495
b1101011011110110 !
1"
#500
0"
#505
b110101101111011 !
1"
#510
0"
#515
b1011010110111101 !
1"
#520
0"
#525
b101101011011110 !
1"
#530
0"
#535
b10110101101111 !
1"
#540
0"
#545
b1011010110111 !
1"
#550
0"
#555
b1000101101011011 !
1"
#560
0"
#565
b100010110101101 !
1"
#570
0"
#575
b10001011010110 !
1"
#580
0"
#585
b1001000101101011 !
1"
#590
0"
#595
b1100100010110101 !
1"
#600
0"
#605
b1110010001011010 !
1"
#610
0"
#615
b1111001000101101 !
1"
#620
0"
#625
b111100100010110 !
1"
#630
0"
#635
b1011110010001011 !
1"
#640
0"
#645
b101111001000101 !
1"
#650
0"
#655
b10111100100010 !
1"
#660
0"
#665
b1001011110010001 !
1"
#670
0"
#675
b1100101111001000 !
1"
#680
0"
#685
b1110010111100100 !
1"
#690
0"
#695
b111001011110010 !
1"
#700
0"
#705
b1011100101111001 !
1"
#710
0"
#715
b1101110010111100 !
1"
#720
0"
#725
b1110111001011110 !
1"
#730
0"
#735
b111011100101111 !
1"
#740
0"
#745
b11101110010111 !
1"
#750
0"
#755
b1110111001011 !
1"
#760
0"
#765
b111011100101 !
1"
#770
0"
#775
b1000011101110010 !
1"
#780
0"
#785
b1100001110111001 !
1"
#790
0"
#795
b1110000111011100 !
1"
#800
0"
#805
b111000011101110 !
1"
#810
0"
#815
b1011100001110111 !
1"
#820
0"
#825
b1101110000111011 !
1"
#830
0"
#835
b1110111000011101 !
1"
#840
0"
#845
b1111011100001110 !
1"
#850
0"
#855
b111101110000111 !
1"
#860
0"
#865
b11110111000011 !
1"
#870
0"
#875
b1001111011100001 !
1"
#880
0"
#885
b100111101110000 !
1"
#890
0"
#895
b1010011110111000 !
1"
#900
0"
#905
b101001111011100 !
1"
#910
0"
#915
b10100111101110 !
1"
#920
0"
#925
b1001010011110111 !
1"
#930
0"
#935
b1100101001111011 !
1"
#940
0"
#945
b1110010100111101 !
1"
#950
0"
#955
b111001010011110 !
1"
#960
0"
#965
b11100101001111 !
1"
#970
0"
#975
b1001110010100111 !
1"
#980
0"
#985
b1100111001010011 !
1"
#990
0"
#995
b1110011100101001 !
1"
#1000
0"
#1005
b1111001110010100 !
1"
#1010
0"
#1015
b1111100111001010 !
1"
#1020
0"
#1025
b1111110011100101 !
1"
